{
	"version": 1,
	"license": "CC-BY-NC-SA-3.0",
	"copyright": "Taken from https://github.com/goonstation/goonstation/blob/77e7dbf9bcc1c1beffa1326000497a3fe23f8142/icons/turf/walls_supernorn_smooth.dmi and modified.",
	"size": {
		"x": 32,
		"y": 32
	},
	"states": [{
			"name": "full"
		},
		{
			"name": "supernorn0",
			"directions": 4
		},
		{
			"name": "supernorn1",
			"directions": 4
		},
		{
			"name": "supernorn2",
			"directions": 4
		},
		{
			"name": "supernorn3",
			"directions": 4
		},
		{
			"name": "supernorn4",
			"directions": 4
		},
		{
			"name": "supernorn5",
			"directions": 4
		},
		{
			"name": "supernorn6",
			"directions": 4
		},
		{
			"name": "supernorn7",
			"directions": 4
		},
		{
			"name": "full_r"
		},
		{
			"name": "reinf_construct-0"
		},
		{
			"name": "reinf_construct-1"
		},
		{
			"name": "reinf_construct-2"
		},
		{
			"name": "reinf_construct-3"
		},
		{
			"name": "reinf_construct-4"
		},
		{
			"name": "reinf_construct-5"
		},
		{
			"name": "supernorn_r0",
			"directions": 4
		},
		{
			"name": "supernorn_r1",
			"directions": 4
		},
		{
			"name": "supernorn_r2",
			"directions": 4
		},
		{
			"name": "supernorn_r3",
			"directions": 4
		},
		{
			"name": "supernorn_r4",
			"directions": 4
		},
		{
			"name": "supernorn_r5",
			"directions": 4
		},
		{
			"name": "supernorn_r6",
			"directions": 4
		},
		{
			"name": "supernorn_r7",
			"directions": 4
		}
	]
}